dataquant_dev/__init__.py
dataquant_dev/apis/__init__.py
dataquant_dev/apis/base/__init__.py
dataquant_dev/apis/base/api.py
dataquant_dev/apis/info/__init__.py
dataquant_dev/apis/info/api.py
dataquant_dev/apis/quote/__init__.py
dataquant_dev/apis/quote/api.py
dataquant_dev/cd/__init__.py
dataquant_dev/cd/api.py
dataquant_dev/hk/__init__.py
dataquant_dev/hk/api.py
dataquant_dev/ibank/__init__.py
dataquant_dev/ibank/api.py
dataquant_dev/ic/__init__.py
dataquant_dev/ic/api.py
dataquant_dev/intl/__init__.py
dataquant_dev/intl/api.py
dataquant_dev/pof/__init__.py
dataquant_dev/pof/api.py
dataquant_dev/sql/__init__.py
dataquant_dev/sql/api.py
dataquant_dev/utils/__init__.py
dataquant_dev/utils/client.py
dataquant_dev/utils/common.py
dataquant_dev/utils/config.py
dataquant_dev/utils/config.yml
dataquant_dev/utils/connection.py
dataquant_dev/utils/connection_pool.py
dataquant_dev/utils/consts.py
dataquant_dev/utils/convert.py
dataquant_dev/utils/datetime_func.py
dataquant_dev/utils/decorators.py
dataquant_dev/utils/error.py
dataquant_dev/utils/parallel.py
dataquant_dev-1.2.1.dist-info/METADATA
dataquant_dev-1.2.1.dist-info/WHEEL
dataquant_dev-1.2.1.dist-info/entry_points.txt
dataquant_dev-1.2.1.dist-info/top_level.txt
dataquant_dev-1.2.1.dist-info/RECORD
