Metadata-Version: 2.1
Name: dataquant-dev
Version: 1.2.1
Author: zszq
Author-email: jiangchao@stocke.com.cn
Keywords: ZHESHANG SECURITES DATA QUANT
Classifier: Intended Audience :: Developers
Classifier: License :: OSI Approved :: GNU General Public License (GPL)
Classifier: Programming Language :: Python
Classifier: Programming Language :: Python :: 3.5
Classifier: Programming Language :: Python :: 3.6
Classifier: Programming Language :: Python :: 3.7
Classifier: Programming Language :: Python :: 3.8
Requires-Dist: numpy (>=1.18.1)
Requires-Dist: six (>=1.13.0)
Requires-Dist: pandas (>=0.24.2)
Requires-Dist: requests (>=2.7.0)
Requires-Dist: contextlib2 (>=0.5.3)
Requires-Dist: simplejson (>=3.17.0)
Requires-Dist: PyYAML (>=3.13)
Requires-Dist: ruamel.yaml (>=0.15.0)
Requires-Dist: gevent (>=1.3.0)
